LICENSE
README.md
setup.py
cnv_suite/__init__.py
cnv_suite.egg-info/PKG-INFO
cnv_suite.egg-info/SOURCES.txt
cnv_suite.egg-info/dependency_links.txt
cnv_suite.egg-info/entry_points.txt
cnv_suite.egg-info/requires.txt
cnv_suite.egg-info/top_level.txt
cnv_suite/compare/__init__.py
cnv_suite/compare/__main__.py
cnv_suite/compare/acr_compare.py
cnv_suite/compare/comparison_validation_tools.py
cnv_suite/compare/plot_acr.py
cnv_suite/simulate/__init__.py
cnv_suite/simulate/cnv_profile.py
cnv_suite/utils/__init__.py
cnv_suite/utils/cnv_helper_methods.py
cnv_suite/utils/simulation_utils.py
cnv_suite/visualize/__init__.py
cnv_suite/visualize/plot_cnv_profile.py