Metadata-Version: 2.1
Name: cnv-suite
Version: 0.1.0
Summary: Copy Number tools for visualization, simulation, and comparison.
Home-page: UNKNOWN
Author: Conor Messer
Author-email: cmesser@broadinstitute.org
License: BSD3
Platform: UNKNOWN
Classifier: Development Status :: 4 - Beta
Classifier: Programming Language :: Python :: 3
Classifier: Intended Audience :: Science/Research
Classifier: Topic :: Scientific/Engineering :: Bio-Informatics
Classifier: License :: OSI Approved :: BSD License
